last_layer/__init__.py
last_layer/__main__.py
last_layer/core.py
last_layer/lib/amazonlinux.so
last_layer/lib/library.so
last_layer/lib/library_linux.so
last_layer/test_core.py
last_layer-0.1.32.dist-info/LICENSE
last_layer-0.1.32.dist-info/METADATA
last_layer-0.1.32.dist-info/WHEEL
last_layer-0.1.32.dist-info/entry_points.txt
last_layer-0.1.32.dist-info/RECORD
