Metadata-Version: 2.1
Name: last_layer
Version: 0.1.32
Summary: Ultra-fast, Low Latency LLM security solution
Home-page: https://github.com/lastlayer/last_layer
License: MIT
Keywords: llm,language model,security,adversarial attacks,prompt injection,prompt leakage,prompt injection attacks,prompt leakage prevention,PII detection,self-hardening
Author: Last Layer
Author-email: gh@tangln.com
Maintainer: Last Layer
Maintainer-email: gh@tangln.com
Requires-Python: >=3.9,<4.0
Classifier: License :: OSI Approved :: MIT License
Classifier: Programming Language :: Python :: 3
Classifier: Programming Language :: Python :: 3.9
Classifier: Programming Language :: Python :: 3.10
Classifier: Programming Language :: Python :: 3.11
Classifier: Programming Language :: Python :: 3.12
Project-URL: Repository, https://github.com/lastlayer/last_layer
